{
    "V_1": {
        "factory_id": "9f1a09c368584eba9e7f10a53d55caae",
        "lng": 116.6309,
        "lat": 40.2304,
        "delivery_item_list": [
            "0020420004-1",
            "0236480009-1",
            "0251190010-1",
            "0315120011-1",
            "0315120011-2",
            "0322400012-1"
        ],
        "pickup_item_list": [],
        "arrive_time": 1699136136.0,
        "leave_time": 0
    },
    "V_2": null,
    "V_3": {
        "factory_id": "32ab2049f3fb437881ff3912470d7840",
        "lng": 116.7112,
        "lat": 40.3527,
        "delivery_item_list": [
            "0047570007-1",
            "0047570007-2"
        ],
        "pickup_item_list": [],
        "arrive_time": 1699135848.0,
        "leave_time": 0
    },
    "V_4": null,
    "V_5": null
}